{
    "보험종류" : 1,
    "손해보험" : "LIG손해", 
    "상품명" : "(무)LIG매직카파워운전자보험",
    "계약자" : "증권번호",
    "계약자_LOC" : -2,
    "납입기간" : "년납 월납",
    "납입기간_LOC" : -1,
    "피보험자" : "피보험자",
    "피보험자_LOC": "-1:0",
    "주석1" : "-1:위,아래   0:왼쪽, 오른쪽   S:split    0: split한 리스트의 0번째",
    "보장기간" : "세만기",
    "보장기간_LOC" : -1,
    "월보장보험료" : "보장 ",
    "월보장보험료_LOC" : 1,
    "계약일" : "계약기간 ",
    "계약일_LOC" : "0:년 월 일:0",
    "만기일" : "계약기간 ",
    "만기일_LOC" : "0:년 월 일:1",
    "월적립보험료" : ": / : ",
    "월적립보험료_LOC" : "0:0:S(원):0",
    "세부사항" : [
        {
            "분류" : "상해사망",
            "위치" : "사망->상해->상해사망",
            "납입기간" : "년",
            "납입기간_LOC" : -1,
            "납입기간단위" : 1,
            "보장기간" : "세",
            "보장기간_LOC" : "0:0:S(/):1",
            "보장기간단위" : 1,
            "보장금액" : "년",
            "보장금액_LOC" : -2
        },
        {
            "분류" : "벌금",
            "위치" : "운전자진단비->벌금->대물 벌금",
            "납입기간" : "년",
            "납입기간_LOC" : -1,
            "납입기간단위" : 1,
            "보장기간" : "세",
            "보장기간_LOC" : "0:0:S(/):1",
            "보장기간단위" : 1,
            "보장금액" : "년",
            "보장금액_LOC" : -2
        }
    ]
}